[
    {
        "find_key_count": 4,
        "find_key_time": 0.016,
        "key_edit_count": 8,
        "key_edit_time": 0.023000000000000003,
        "crypto_init_count": 242,
        "crypto_init_time": 0.2840000000000002,
        "crypto_update_count": 829,
        "crypto_update_time": 0.9180000000000007
    },
    {
        "find_key_count": 4,
        "find_key_time": 0.017,
        "key_edit_count": 8,
        "key_edit_time": 0.023000000000000003,
        "crypto_init_count": 242,
        "crypto_init_time": 0.3030000000000002,
        "crypto_update_count": 829,
        "crypto_update_time": 0.8900000000000007
    },
    {
        "find_key_count": 4,
        "find_key_time": 0.016,
        "key_edit_count": 8,
        "key_edit_time": 0.023000000000000003,
        "crypto_init_count": 242,
        "crypto_init_time": 0.2940000000000002,
        "crypto_update_count": 829,
        "crypto_update_time": 0.8980000000000007
    }
]