[
    {
        "find_key_count": 4,
        "find_key_time": 0.024,
        "key_edit_count": 8,
        "key_edit_time": 0.031,
        "crypto_init_count": 173,
        "crypto_init_time": 0.3770000000000003,
        "crypto_update_count": 570,
        "crypto_update_time": 0.5110000000000003
    },
    {
        "find_key_count": 4,
        "find_key_time": 0.024,
        "key_edit_count": 8,
        "key_edit_time": 0.032,
        "crypto_init_count": 173,
        "crypto_init_time": 0.3740000000000003,
        "crypto_update_count": 570,
        "crypto_update_time": 0.4900000000000004
    },
    {
        "find_key_count": 4,
        "find_key_time": 0.023,
        "key_edit_count": 8,
        "key_edit_time": 0.031,
        "crypto_init_count": 173,
        "crypto_init_time": 0.3790000000000003,
        "crypto_update_count": 570,
        "crypto_update_time": 0.4880000000000004
    }
]